{
  "validation": {
    "accuracy": 0.7543859649122807,
    "precision": 0.7432054413842666,
    "recall": 0.7543859649122807,
    "f1": 0.7441099029889985,
    "auc": 0.802106940509915,
    "precision_per_class": [
      0.639344262295082,
      0.7902813299232737
    ],
    "recall_per_class": [
      0.4875,
      0.8753541076487252
    ],
    "f1_per_class": [
      0.5531914893617021,
      0.8306451612903226
    ],
    "support_per_class": [
      160,
      353
    ],
    "confusion_matrix": [
      [
        78,
        82
      ],
      [
        44,
        309
      ]
    ],
    "classification_report": {
      "clickbait": {
        "precision": 0.639344262295082,
        "recall": 0.4875,
        "f1-score": 0.5531914893617021,
        "support": 160.0
      },
      "non-clickbait": {
        "precision": 0.7902813299232737,
        "recall": 0.8753541076487252,
        "f1-score": 0.8306451612903226,
        "support": 353.0
      },
      "accuracy": 0.7543859649122807,
      "macro avg": {
        "precision": 0.7148127961091779,
        "recall": 0.6814270538243626,
        "f1-score": 0.6919183253260124,
        "support": 513.0
      },
      "weighted avg": {
        "precision": 0.7432054413842666,
        "recall": 0.7543859649122807,
        "f1-score": 0.7441099029889985,
        "support": 513.0
      }
    },
    "predictions": [
      "non-clickbait",
      "non-clickbait",
      "non-clickbait",
      "non-clickbait",
      "clickbait",
      "non-clickbait",
      "non-clickbait",
      "clickbait",
      "clickbait",
      "non-clickbait",
      "non-clickbait",
      "non-clickbait",
      "clickbait",
      "clickbait",
      "non-clickbait",
      "clickbait",
      "non-clickbait",
      "clickbait",
      "non-clickbait",
      "non-clickbait",
      "non-clickbait",
      "non-clickbait",
      "non-clickbait",
      "clickbait",
      "non-clickbait",
      "clickbait",
      "clickbait",
      "non-clickbait",
      "non-clickbait",
      "non-clickbait",
      "non-clickbait",
      "non-clickbait",
      "non-clickbait",
      "non-clickbait",
      "non-clickbait",
      "non-clickbait",
      "non-clickbait",
      "non-clickbait",
      "clickbait",
      "non-clickbait",
      "non-clickbait",
      "non-clickbait",
      "non-clickbait",
      "non-clickbait",
      "non-clickbait",
      "non-clickbait",
      "non-clickbait",
      "non-clickbait",
      "non-clickbait",
      "non-clickbait",
      "non-clickbait",
      "non-clickbait",
      "non-clickbait",
      "non-clickbait",
      "non-clickbait",
      "non-clickbait",
      "non-clickbait",
      "clickbait",
      "non-clickbait",
      "non-clickbait",
      "non-clickbait",
      "clickbait",
      "non-clickbait",
      "non-clickbait",
      "non-clickbait",
      "non-clickbait",
      "non-clickbait",
      "non-clickbait",
      "clickbait",
      "clickbait",
      "non-clickbait",
      "non-clickbait",
      "non-clickbait",
      "non-clickbait",
      "non-clickbait",
      "non-clickbait",
      "non-clickbait",
      "non-clickbait",
      "non-clickbait",
      "non-clickbait",
      "non-clickbait",
      "non-clickbait",
      "clickbait",
      "non-clickbait",
      "clickbait",
      "non-clickbait",
      "clickbait",
      "non-clickbait",
      "non-clickbait",
      "non-clickbait",
      "clickbait",
      "clickbait",
      "non-clickbait",
      "non-clickbait",
      "non-clickbait",
      "non-clickbait",
      "non-clickbait",
      "clickbait",
      "non-clickbait",
      "non-clickbait",
      "non-clickbait",
      "clickbait",
      "non-clickbait",
      "clickbait",
      "clickbait",
      "clickbait",
      "non-clickbait",
      "non-clickbait",
      "non-clickbait",
      "non-clickbait",
      "clickbait",
      "clickbait",
      "non-clickbait",
      "non-clickbait",
      "clickbait",
      "non-clickbait",
      "non-clickbait",
      "non-clickbait",
      "clickbait",
      "non-clickbait",
      "clickbait",
      "clickbait",
      "non-clickbait",
      "non-clickbait",
      "clickbait",
      "non-clickbait",
      "clickbait",
      "non-clickbait",
      "non-clickbait",
      "non-clickbait",
      "non-clickbait",
      "clickbait",
      "clickbait",
      "non-clickbait",
      "clickbait",
      "non-clickbait",
      "clickbait",
      "non-clickbait",
      "clickbait",
      "non-clickbait",
      "non-clickbait",
      "clickbait",
      "non-clickbait",
      "clickbait",
      "non-clickbait",
      "non-clickbait",
      "non-clickbait",
      "non-clickbait",
      "non-clickbait",
      "non-clickbait",
      "clickbait",
      "clickbait",
      "non-clickbait",
      "non-clickbait",
      "clickbait",
      "non-clickbait",
      "clickbait",
      "non-clickbait",
      "non-clickbait",
      "clickbait",
      "non-clickbait",
      "non-clickbait",
      "non-clickbait",
      "non-clickbait",
      "non-clickbait",
      "non-clickbait",
      "non-clickbait",
      "clickbait",
      "non-clickbait",
      "non-clickbait",
      "non-clickbait",
      "non-clickbait",
      "non-clickbait",
      "non-clickbait",
      "non-clickbait",
      "clickbait",
      "non-clickbait",
      "non-clickbait",
      "clickbait",
      "clickbait",
      "non-clickbait",
      "non-clickbait",
      "non-clickbait",
      "non-clickbait",
      "non-clickbait",
      "non-clickbait",
      "non-clickbait",
      "clickbait",
      "non-clickbait",
      "non-clickbait",
      "clickbait",
      "non-clickbait",
      "non-clickbait",
      "non-clickbait",
      "non-clickbait",
      "non-clickbait",
      "clickbait",
      "non-clickbait",
      "non-clickbait",
      "clickbait",
      "clickbait",
      "non-clickbait",
      "non-clickbait",
      "clickbait",
      "non-clickbait",
      "non-clickbait",
      "non-clickbait",
      "non-clickbait",
      "clickbait",
      "non-clickbait",
      "non-clickbait",
      "clickbait",
      "clickbait",
      "non-clickbait",
      "non-clickbait",
      "non-clickbait",
      "non-clickbait",
      "clickbait",
      "non-clickbait",
      "clickbait",
      "clickbait",
      "non-clickbait",
      "clickbait",
      "non-clickbait",
      "non-clickbait",
      "non-clickbait",
      "non-clickbait",
      "non-clickbait",
      "non-clickbait",
      "clickbait",
      "non-clickbait",
      "non-clickbait",
      "non-clickbait",
      "non-clickbait",
      "non-clickbait",
      "non-clickbait",
      "non-clickbait",
      "non-clickbait",
      "non-clickbait",
      "non-clickbait",
      "non-clickbait",
      "non-clickbait",
      "non-clickbait",
      "non-clickbait",
      "non-clickbait",
      "non-clickbait",
      "non-clickbait",
      "non-clickbait",
      "non-clickbait",
      "non-clickbait",
      "non-clickbait",
      "non-clickbait",
      "non-clickbait",
      "non-clickbait",
      "non-clickbait",
      "clickbait",
      "non-clickbait",
      "non-clickbait",
      "non-clickbait",
      "clickbait",
      "non-clickbait",
      "non-clickbait",
      "non-clickbait",
      "non-clickbait",
      "non-clickbait",
      "non-clickbait",
      "non-clickbait",
      "non-clickbait",
      "clickbait",
      "non-clickbait",
      "clickbait",
      "clickbait",
      "non-clickbait",
      "non-clickbait",
      "clickbait",
      "non-clickbait",
      "clickbait",
      "non-clickbait",
      "clickbait",
      "non-clickbait",
      "non-clickbait",
      "non-clickbait",
      "non-clickbait",
      "non-clickbait",
      "non-clickbait",
      "non-clickbait",
      "non-clickbait",
      "non-clickbait",
      "non-clickbait",
      "non-clickbait",
      "non-clickbait",
      "non-clickbait",
      "clickbait",
      "non-clickbait",
      "non-clickbait",
      "non-clickbait",
      "non-clickbait",
      "non-clickbait",
      "non-clickbait",
      "non-clickbait",
      "non-clickbait",
      "non-clickbait",
      "clickbait",
      "clickbait",
      "non-clickbait",
      "non-clickbait",
      "non-clickbait",
      "non-clickbait",
      "non-clickbait",
      "non-clickbait",
      "non-clickbait",
      "non-clickbait",
      "non-clickbait",
      "non-clickbait",
      "clickbait",
      "non-clickbait",
      "clickbait",
      "non-clickbait",
      "non-clickbait",
      "non-clickbait",
      "clickbait",
      "non-clickbait",
      "non-clickbait",
      "non-clickbait",
      "non-clickbait",
      "non-clickbait",
      "non-clickbait",
      "non-clickbait",
      "clickbait",
      "non-clickbait",
      "non-clickbait",
      "non-clickbait",
      "non-clickbait",
      "non-clickbait",
      "non-clickbait",
      "non-clickbait",
      "clickbait",
      "non-clickbait",
      "non-clickbait",
      "non-clickbait",
      "non-clickbait",
      "non-clickbait",
      "non-clickbait",
      "non-clickbait",
      "non-clickbait",
      "non-clickbait",
      "non-clickbait",
      "non-clickbait",
      "non-clickbait",
      "clickbait",
      "non-clickbait",
      "non-clickbait",
      "non-clickbait",
      "non-clickbait",
      "non-clickbait",
      "non-clickbait",
      "clickbait",
      "non-clickbait",
      "non-clickbait",
      "non-clickbait",
      "non-clickbait",
      "non-clickbait",
      "non-clickbait",
      "clickbait",
      "non-clickbait",
      "clickbait",
      "non-clickbait",
      "non-clickbait",
      "clickbait",
      "non-clickbait",
      "non-clickbait",
      "non-clickbait",
      "clickbait",
      "non-clickbait",
      "clickbait",
      "non-clickbait",
      "non-clickbait",
      "clickbait",
      "clickbait",
      "non-clickbait",
      "non-clickbait",
      "clickbait",
      "non-clickbait",
      "non-clickbait",
      "non-clickbait",
      "non-clickbait",
      "non-clickbait",
      "non-clickbait",
      "clickbait",
      "non-clickbait",
      "non-clickbait",
      "non-clickbait",
      "non-clickbait",
      "non-clickbait",
      "non-clickbait",
      "non-clickbait",
      "clickbait",
      "non-clickbait",
      "non-clickbait",
      "clickbait",
      "clickbait",
      "non-clickbait",
      "non-clickbait",
      "non-clickbait",
      "non-clickbait",
      "non-clickbait",
      "non-clickbait",
      "non-clickbait",
      "non-clickbait",
      "non-clickbait",
      "non-clickbait",
      "non-clickbait",
      "non-clickbait",
      "non-clickbait",
      "non-clickbait",
      "non-clickbait",
      "non-clickbait",
      "non-clickbait",
      "non-clickbait",
      "non-clickbait",
      "non-clickbait",
      "non-clickbait",
      "non-clickbait",
      "clickbait",
      "non-clickbait",
      "non-clickbait",
      "non-clickbait",
      "clickbait",
      "non-clickbait",
      "clickbait",
      "non-clickbait",
      "clickbait",
      "non-clickbait",
      "clickbait",
      "non-clickbait",
      "non-clickbait",
      "clickbait",
      "clickbait",
      "non-clickbait",
      "non-clickbait",
      "non-clickbait",
      "non-clickbait",
      "non-clickbait",
      "non-clickbait",
      "non-clickbait",
      "clickbait",
      "non-clickbait",
      "non-clickbait",
      "non-clickbait",
      "non-clickbait",
      "non-clickbait",
      "clickbait",
      "clickbait",
      "non-clickbait",
      "non-clickbait",
      "clickbait",
      "non-clickbait",
      "non-clickbait",
      "non-clickbait",
      "non-clickbait",
      "non-clickbait",
      "clickbait",
      "non-clickbait",
      "non-clickbait",
      "clickbait",
      "non-clickbait",
      "clickbait",
      "clickbait",
      "non-clickbait",
      "non-clickbait",
      "clickbait",
      "non-clickbait",
      "non-clickbait",
      "non-clickbait",
      "non-clickbait",
      "clickbait",
      "clickbait",
      "non-clickbait",
      "non-clickbait",
      "clickbait",
      "clickbait",
      "non-clickbait",
      "non-clickbait",
      "non-clickbait",
      "non-clickbait",
      "non-clickbait",
      "non-clickbait",
      "clickbait",
      "non-clickbait",
      "clickbait",
      "non-clickbait",
      "clickbait",
      "non-clickbait",
      "non-clickbait",
      "non-clickbait",
      "non-clickbait",
      "clickbait",
      "non-clickbait",
      "clickbait",
      "non-clickbait",
      "clickbait",
      "non-clickbait",
      "non-clickbait",
      "non-clickbait",
      "clickbait",
      "clickbait",
      "clickbait",
      "non-clickbait",
      "non-clickbait",
      "non-clickbait",
      "non-clickbait",
      "non-clickbait",
      "non-clickbait"
    ],
    "probabilities": [
      [
        0.12003598439508914,
        0.8799640156049111
      ],
      [
        0.14637788400739898,
        0.8536221159926011
      ],
      [
        0.3239993367991161,
        0.6760006632008841
      ],
      [
        0.27255632754298637,
        0.7274436724570136
      ],
      [
        0.658088707030955,
        0.34191129296904516
      ],
      [
        0.1915022998255768,
        0.8084977001744234
      ],
      [
        0.0686839856060254,
        0.9313160143939745
      ],
      [
        0.7588407848334181,
        0.241159215166582
      ],
      [
        0.6548805922482156,
        0.3451194077517844
      ],
      [
        0.3250351624467731,
        0.6749648375532271
      ],
      [
        0.3649735050388429,
        0.635026494961157
      ],
      [
        0.39024033808291037,
        0.6097596619170895
      ],
      [
        0.7314451866843505,
        0.26855481331564934
      ],
      [
        0.748735925743413,
        0.25126407425658726
      ],
      [
        0.4263136671712223,
        0.5736863328287777
      ],
      [
        0.987108185088901,
        0.01289181491109909
      ],
      [
        0.1867517703475346,
        0.8132482296524653
      ],
      [
        0.921411464402297,
        0.07858853559770314
      ],
      [
        0.03719263658194339,
        0.9628073634180565
      ],
      [
        0.15652252187892154,
        0.8434774781210783
      ],
      [
        0.07076010106213305,
        0.929239898937867
      ],
      [
        0.018810407151976866,
        0.9811895928480231
      ],
      [
        0.06499203622280356,
        0.9350079637771964
      ],
      [
        0.6236030856557931,
        0.376396914344207
      ],
      [
        0.12411987518228854,
        0.8758801248177114
      ],
      [
        0.8591335358728348,
        0.14086646412716522
      ],
      [
        0.5601355930252243,
        0.43986440697477575
      ],
      [
        0.07827558489200488,
        0.9217244151079951
      ],
      [
        0.4822127726301786,
        0.5177872273698215
      ],
      [
        0.09322407470030669,
        0.9067759252996934
      ],
      [
        0.1591346250422783,
        0.8408653749577214
      ],
      [
        0.05374977354503299,
        0.946250226454967
      ],
      [
        0.21256318507839383,
        0.7874368149216066
      ],
      [
        0.22225106367134465,
        0.7777489363286555
      ],
      [
        0.3063826500035917,
        0.6936173499964082
      ],
      [
        0.5237013863572518,
        0.47629861364274817
      ],
      [
        0.3299226481884042,
        0.6700773518115958
      ],
      [
        0.14045800201425027,
        0.8595419979857496
      ],
      [
        0.7665733063361228,
        0.23342669366387758
      ],
      [
        0.11297795760642072,
        0.8870220423935792
      ],
      [
        0.12034688129718081,
        0.8796531187028191
      ],
      [
        0.04296670445731177,
        0.9570332955426882
      ],
      [
        0.0876531605181032,
        0.9123468394818969
      ],
      [
        0.3089645630459543,
        0.6910354369540458
      ],
      [
        0.06341348670706543,
        0.9365865132929346
      ],
      [
        0.2798040041586882,
        0.7201959958413116
      ],
      [
        0.40743025033393604,
        0.592569749666064
      ],
      [
        0.3851551234697048,
        0.6148448765302951
      ],
      [
        0.031357812047752495,
        0.9686421879522475
      ],
      [
        0.037378146170567825,
        0.9626218538294323
      ],
      [
        0.07311788673658363,
        0.9268821132634164
      ],
      [
        0.4798618187297875,
        0.5201381812702125
      ],
      [
        0.42352468465875015,
        0.5764753153412497
      ],
      [
        0.20250909245657073,
        0.7974909075434293
      ],
      [
        0.035535054310631725,
        0.9644649456893682
      ],
      [
        0.1261359428754157,
        0.8738640571245841
      ],
      [
        0.5208592739998571,
        0.4791407260001429
      ],
      [
        0.9958894510893487,
        0.004110548910651326
      ],
      [
        0.1263164270020835,
        0.8736835729979167
      ],
      [
        0.3915067205373746,
        0.6084932794626253
      ],
      [
        0.08270753966226475,
        0.9172924603377353
      ],
      [
        0.8551381012316795,
        0.1448618987683203
      ],
      [
        0.07241049663407363,
        0.9275895033659264
      ],
      [
        0.1209361773460842,
        0.8790638226539158
      ],
      [
        0.10118669121919494,
        0.8988133087808051
      ],
      [
        0.13488879336255255,
        0.8651112066374474
      ],
      [
        0.27940347575545815,
        0.7205965242445418
      ],
      [
        0.32441518335059727,
        0.6755848166494028
      ],
      [
        0.7151863638905491,
        0.28481363610945093
      ],
      [
        0.6839755874065826,
        0.31602441259341735
      ],
      [
        0.3057432857628196,
        0.6942567142371802
      ],
      [
        0.07800394704981739,
        0.9219960529501828
      ],
      [
        0.49249416202809404,
        0.507505837971906
      ],
      [
        0.04117213677953797,
        0.9588278632204621
      ],
      [
        0.0968774249534011,
        0.9031225750465988
      ],
      [
        0.058098689528356784,
        0.9419013104716433
      ],
      [
        0.5394861449536565,
        0.46051385504634357
      ],
      [
        0.1701497971450331,
        0.8298502028549669
      ],
      [
        0.028315138659088093,
        0.971684861340912
      ],
      [
        0.05507585535266494,
        0.9449241446473352
      ],
      [
        0.07593561721106509,
        0.9240643827889349
      ],
      [
        0.038525497032535064,
        0.9614745029674652
      ],
      [
        0.9208093121249955,
        0.07919068787500455
      ],
      [
        0.1486719223717986,
        0.8513280776282014
      ],
      [
        0.8684221812172169,
        0.13157781878278313
      ],
      [
        0.04843551177379335,
        0.9515644882262067
      ],
      [
        0.7638113453142963,
        0.2361886546857037
      ],
      [
        0.42294294400620736,
        0.5770570559937926
      ],
      [
        0.047338282430059685,
        0.9526617175699403
      ],
      [
        0.47045794279733183,
        0.5295420572026681
      ],
      [
        0.6361419085255694,
        0.36385809147443055
      ],
      [
        0.618574946009558,
        0.3814250539904421
      ],
      [
        0.21383897942690167,
        0.7861610205730983
      ],
      [
        0.2016397016510217,
        0.7983602983489783
      ],
      [
        0.2586730817568443,
        0.7413269182431558
      ],
      [
        0.17853414293098885,
        0.821465857069011
      ],
      [
        0.03174029977997631,
        0.9682597002200238
      ],
      [
        0.7676589334602398,
        0.23234106653976017
      ],
      [
        0.014292473726107216,
        0.9857075262738928
      ],
      [
        0.15386511628821928,
        0.8461348837117807
      ],
      [
        0.11615372947148278,
        0.8838462705285173
      ],
      [
        0.8953464512508607,
        0.1046535487491393
      ],
      [
        0.18200564118810858,
        0.8179943588118915
      ],
      [
        0.8027477451301626,
        0.19725225486983727
      ],
      [
        0.9151111309364448,
        0.08488886906355542
      ],
      [
        0.614340685931387,
        0.3856593140686131
      ],
      [
        0.21021692779647835,
        0.7897830722035216
      ],
      [
        0.05767127889031903,
        0.9423287211096809
      ],
      [
        0.10410985775473262,
        0.8958901422452674
      ],
      [
        0.536964388943095,
        0.46303561105690505
      ],
      [
        0.9626609379127868,
        0.03733906208721312
      ],
      [
        0.5636503749499071,
        0.4363496250500929
      ],
      [
        0.2865430401871612,
        0.7134569598128387
      ],
      [
        0.508057716768083,
        0.49194228323191697
      ],
      [
        0.9704997185207138,
        0.029500281479286183
      ],
      [
        0.13208131418726438,
        0.8679186858127357
      ],
      [
        0.07189919736442352,
        0.9281008026355763
      ],
      [
        0.07365131806641333,
        0.9263486819335867
      ],
      [
        0.8664084545955432,
        0.13359154540445675
      ],
      [
        0.14362919703800495,
        0.8563708029619949
      ],
      [
        0.8448538242565837,
        0.1551461757434164
      ],
      [
        0.8040970772567351,
        0.195902922743265
      ],
      [
        0.3133887113643578,
        0.686611288635642
      ],
      [
        0.5194264215661002,
        0.4805735784338998
      ],
      [
        0.6266623638189933,
        0.37333763618100657
      ],
      [
        0.5148092632138843,
        0.48519073678611574
      ],
      [
        0.826822157698015,
        0.17317784230198485
      ],
      [
        0.03299301410452904,
        0.9670069858954712
      ],
      [
        0.18195458897955383,
        0.818045411020446
      ],
      [
        0.13922835986482426,
        0.8607716401351757
      ],
      [
        0.116297366730505,
        0.8837026332694947
      ],
      [
        0.6388492399431376,
        0.36115076005686253
      ],
      [
        0.5757223132474933,
        0.4242776867525065
      ],
      [
        0.43249312032145537,
        0.5675068796785445
      ],
      [
        0.9301555722445591,
        0.06984442775544064
      ],
      [
        0.07566220196271196,
        0.9243377980372879
      ],
      [
        0.6316629533763,
        0.3683370466236999
      ],
      [
        0.5111268987253824,
        0.4888731012746176
      ],
      [
        0.820128222886412,
        0.17987177711358784
      ],
      [
        0.3541011467125177,
        0.6458988532874823
      ],
      [
        0.1730570639888221,
        0.826942936011178
      ],
      [
        0.920377998216864,
        0.07962200178313605
      ],
      [
        0.36611513613169744,
        0.6338848638683026
      ],
      [
        0.9470771987578288,
        0.05292280124217128
      ],
      [
        0.11866035640931155,
        0.8813396435906883
      ],
      [
        0.16776410334519656,
        0.8322358966548035
      ],
      [
        0.05119978694573519,
        0.9488002130542648
      ],
      [
        0.0501886766744313,
        0.9498113233255686
      ],
      [
        0.04130974561748842,
        0.9586902543825117
      ],
      [
        0.014268585695018992,
        0.9857314143049809
      ],
      [
        0.6928671834505122,
        0.30713281654948765
      ],
      [
        0.5616831511737326,
        0.43831684882626737
      ],
      [
        0.4331301225644607,
        0.5668698774355392
      ],
      [
        0.09982358663830704,
        0.900176413361693
      ],
      [
        0.7547596303382348,
        0.24524036966176532
      ],
      [
        0.05481872467405024,
        0.9451812753259496
      ],
      [
        0.8904642035193754,
        0.10953579648062461
      ],
      [
        0.06387112248558006,
        0.9361288775144198
      ],
      [
        0.3857469885361008,
        0.6142530114638994
      ],
      [
        0.6113393008862259,
        0.38866069911377404
      ],
      [
        0.2577898637983835,
        0.7422101362016165
      ],
      [
        0.10010009626745836,
        0.8998999037325416
      ],
      [
        0.027005096419548104,
        0.9729949035804518
      ],
      [
        0.20113620098484275,
        0.7988637990151572
      ],
      [
        0.029587291151604064,
        0.970412708848396
      ],
      [
        0.08817063918226445,
        0.9118293608177356
      ],
      [
        0.03355344730731543,
        0.9664465526926845
      ],
      [
        0.9092363661921754,
        0.0907636338078247
      ],
      [
        0.07112424244053936,
        0.9288757575594605
      ],
      [
        0.18558369169030522,
        0.8144163083096948
      ],
      [
        0.2819399944867675,
        0.7180600055132329
      ],
      [
        0.30459933737413875,
        0.6954006626258613
      ],
      [
        0.066801812086837,
        0.933198187913163
      ],
      [
        0.024520368799686398,
        0.9754796312003136
      ],
      [
        0.18157633041472782,
        0.8184236695852724
      ],
      [
        0.697609130918848,
        0.30239086908115215
      ],
      [
        0.0790338657210659,
        0.9209661342789341
      ],
      [
        0.2041104068697715,
        0.7958895931302287
      ],
      [
        0.905802916463237,
        0.0941970835367629
      ],
      [
        0.7211562141210276,
        0.27884378587897246
      ],
      [
        0.16576698540870047,
        0.8342330145912994
      ],
      [
        0.06801431273578139,
        0.9319856872642187
      ],
      [
        0.09388167513447573,
        0.9061183248655243
      ],
      [
        0.06463410199171608,
        0.935365898008284
      ],
      [
        0.26025374788482336,
        0.7397462521151766
      ],
      [
        0.4625862337476612,
        0.5374137662523388
      ],
      [
        0.06634523877056586,
        0.9336547612294342
      ],
      [
        0.5949598840749466,
        0.4050401159250533
      ],
      [
        0.40195580194525565,
        0.5980441980547444
      ],
      [
        0.05747299800403681,
        0.9425270019959632
      ],
      [
        0.9520498943936169,
        0.04795010560638328
      ],
      [
        0.37324137401013047,
        0.6267586259898695
      ],
      [
        0.5189939508906559,
        0.4810060491093441
      ],
      [
        0.048888978873696705,
        0.9511110211263032
      ],
      [
        0.18231459497121139,
        0.8176854050287887
      ],
      [
        0.05363317024778923,
        0.9463668297522109
      ],
      [
        0.568394307039285,
        0.4316056929607152
      ],
      [
        0.11828934874510147,
        0.8817106512548984
      ],
      [
        0.3224799118480995,
        0.6775200881519005
      ],
      [
        0.7338936338345148,
        0.2661063661654852
      ],
      [
        0.852105042857819,
        0.14789495714218082
      ],
      [
        0.02555819502285422,
        0.9744418049771458
      ],
      [
        0.14921765420025013,
        0.8507823457997499
      ],
      [
        0.8613075381155658,
        0.1386924618844342
      ],
      [
        0.2171541295324591,
        0.782845870467541
      ],
      [
        0.3114583867521023,
        0.6885416132478975
      ],
      [
        0.06924592483635265,
        0.9307540751636473
      ],
      [
        0.13386439927345326,
        0.8661356007265466
      ],
      [
        0.6406802831597084,
        0.3593197168402915
      ],
      [
        0.03885421328001099,
        0.9611457867199891
      ],
      [
        0.4111533458564181,
        0.588846654143582
      ],
      [
        0.6662489589987117,
        0.33375104100128833
      ],
      [
        0.7553095970417906,
        0.24469040295820926
      ],
      [
        0.13913203886312742,
        0.8608679611368725
      ],
      [
        0.10325796652921947,
        0.8967420334707806
      ],
      [
        0.2740452667489071,
        0.7259547332510928
      ],
      [
        0.3510341487828294,
        0.6489658512171708
      ],
      [
        0.7284305349481628,
        0.27156946505183754
      ],
      [
        0.07761983949769476,
        0.9223801605023052
      ],
      [
        0.5534167573073391,
        0.44658324269266086
      ],
      [
        0.5981727089544833,
        0.4018272910455167
      ],
      [
        0.5186744589913782,
        0.4813255410086217
      ],
      [
        0.8659478198575311,
        0.134052180142469
      ],
      [
        0.4412756138667095,
        0.5587243861332905
      ],
      [
        0.13863191710407427,
        0.8613680828959257
      ],
      [
        0.03957066090215309,
        0.960429339097847
      ],
      [
        0.322244240115955,
        0.677755759884045
      ],
      [
        0.5,
        0.5
      ],
      [
        0.06695634307665173,
        0.9330436569233482
      ],
      [
        0.6682004413544945,
        0.3317995586455053
      ],
      [
        0.02042212279705106,
        0.9795778772029488
      ],
      [
        0.28066549885513664,
        0.7193345011448634
      ],
      [
        0.474800632316936,
        0.5251993676830641
      ],
      [
        0.03903369287845158,
        0.9609663071215484
      ],
      [
        0.038135275468489216,
        0.9618647245315108
      ],
      [
        0.18936869429457487,
        0.8106313057054251
      ],
      [
        0.5,
        0.5
      ],
      [
        0.045700813461759186,
        0.9542991865382409
      ],
      [
        0.3442348175111468,
        0.655765182488853
      ],
      [
        0.3521565958114928,
        0.6478434041885072
      ],
      [
        0.04328613723307077,
        0.9567138627669294
      ],
      [
        0.05183113882820836,
        0.9481688611717917
      ],
      [
        0.046279008661993866,
        0.9537209913380063
      ],
      [
        0.2947706010883686,
        0.7052293989116314
      ],
      [
        0.03028350015773854,
        0.9697164998422616
      ],
      [
        0.10230385159971457,
        0.8976961484002851
      ],
      [
        0.20122626689567322,
        0.7987737331043269
      ],
      [
        0.15914405077643365,
        0.840855949223566
      ],
      [
        0.5304413585966696,
        0.46955864140333037
      ],
      [
        0.19983105361687,
        0.8001689463831299
      ],
      [
        0.12889948235242477,
        0.8711005176475752
      ],
      [
        0.027869816497501667,
        0.9721301835024985
      ],
      [
        0.2250326750611297,
        0.7749673249388702
      ],
      [
        0.3587433538246836,
        0.6412566461753165
      ],
      [
        0.2279681795158525,
        0.7720318204841472
      ],
      [
        0.5926810146219677,
        0.40731898537803224
      ],
      [
        0.1605774149848733,
        0.8394225850151267
      ],
      [
        0.18443636875767985,
        0.8155636312423201
      ],
      [
        0.4177080098466379,
        0.5822919901533621
      ],
      [
        0.9726740536882025,
        0.027325946311797553
      ],
      [
        0.13075583350284076,
        0.8692441664971591
      ],
      [
        0.15118364495841874,
        0.8488163550415814
      ],
      [
        0.029141431816319834,
        0.9708585681836801
      ],
      [
        0.17559768327500003,
        0.8244023167249999
      ],
      [
        0.08794880745508253,
        0.9120511925449173
      ],
      [
        0.4935655604282888,
        0.5064344395717112
      ],
      [
        0.07827875176424134,
        0.9217212482357587
      ],
      [
        0.11401812337260431,
        0.8859818766273958
      ],
      [
        0.8662382624801588,
        0.1337617375198413
      ],
      [
        0.14332099975095788,
        0.8566790002490421
      ],
      [
        0.8180658225419796,
        0.18193417745802043
      ],
      [
        0.5444688887556044,
        0.4555311112443954
      ],
      [
        0.2310887328356017,
        0.7689112671643985
      ],
      [
        0.09175666130868194,
        0.908243338691318
      ],
      [
        0.7706922305686507,
        0.22930776943134934
      ],
      [
        0.08042210459574127,
        0.9195778954042586
      ],
      [
        0.7957621337998869,
        0.20423786620011306
      ],
      [
        0.08476196153520092,
        0.9152380384647991
      ],
      [
        0.8656258683315032,
        0.13437413166849682
      ],
      [
        0.03428003117376284,
        0.965719968826237
      ],
      [
        0.3529531947193563,
        0.6470468052806437
      ],
      [
        0.2795985782295282,
        0.7204014217704717
      ],
      [
        0.2959857307104672,
        0.7040142692895329
      ],
      [
        0.024539547653130146,
        0.9754604523468698
      ],
      [
        0.24323907697504824,
        0.756760923024952
      ],
      [
        0.12109281646966136,
        0.8789071835303387
      ],
      [
        0.2580768985312886,
        0.7419231014687114
      ],
      [
        0.43511611842817316,
        0.5648838815718268
      ],
      [
        0.28961479322955075,
        0.7103852067704491
      ],
      [
        0.4262807963905749,
        0.573719203609425
      ],
      [
        0.22742555127147113,
        0.7725744487285289
      ],
      [
        0.3546034424403015,
        0.6453965575596985
      ],
      [
        0.7673742244513133,
        0.2326257755486868
      ],
      [
        0.0837771664335279,
        0.9162228335664723
      ],
      [
        0.16379643661464866,
        0.8362035633853514
      ],
      [
        0.11858899687934922,
        0.8814110031206509
      ],
      [
        0.13411376189824534,
        0.8658862381017546
      ],
      [
        0.3823287646295919,
        0.6176712353704081
      ],
      [
        0.45616135645028505,
        0.543838643549715
      ],
      [
        0.056259884037909914,
        0.9437401159620901
      ],
      [
        0.0587612382272543,
        0.9412387617727456
      ],
      [
        0.3532962263741164,
        0.6467037736258837
      ],
      [
        0.7203767729622665,
        0.2796232270377334
      ],
      [
        0.664088844975485,
        0.33591115502451485
      ],
      [
        0.06774904488848212,
        0.9322509551115181
      ],
      [
        0.5314373768868798,
        0.4685626231131202
      ],
      [
        0.1074779797679697,
        0.8925220202320304
      ],
      [
        0.4301776979495568,
        0.569822302050443
      ],
      [
        0.07119129296648348,
        0.9288087070335166
      ],
      [
        0.5357092981680709,
        0.464290701831929
      ],
      [
        0.16797280008302543,
        0.8320271999169746
      ],
      [
        0.28688111908897185,
        0.7131188809110282
      ],
      [
        0.11955721561957433,
        0.8804427843804257
      ],
      [
        0.5302209634103889,
        0.46977903658961123
      ],
      [
        0.6471046601356111,
        0.35289533986438887
      ],
      [
        0.1089968615337726,
        0.8910031384662274
      ],
      [
        0.9393937552850027,
        0.0606062447149973
      ],
      [
        0.2718460324175609,
        0.7281539675824392
      ],
      [
        0.029707738779786448,
        0.9702922612202136
      ],
      [
        0.2821261360966467,
        0.7178738639033532
      ],
      [
        0.8497612416162931,
        0.15023875838370696
      ],
      [
        0.07733213130765476,
        0.9226678686923454
      ],
      [
        0.2998376306461714,
        0.7001623693538287
      ],
      [
        0.32717842478213377,
        0.6728215752178661
      ],
      [
        0.16676421555070453,
        0.8332357844492956
      ],
      [
        0.03943348811695446,
        0.9605665118830456
      ],
      [
        0.45217149226898984,
        0.5478285077310101
      ],
      [
        0.40991901042855644,
        0.5900809895714434
      ],
      [
        0.7091198008637171,
        0.290880199136283
      ],
      [
        0.4262755868897313,
        0.5737244131102688
      ],
      [
        0.17005121630907657,
        0.8299487836909234
      ],
      [
        0.1277473133262875,
        0.8722526866737125
      ],
      [
        0.24006192142103192,
        0.7599380785789681
      ],
      [
        0.04315443021829042,
        0.9568455697817095
      ],
      [
        0.18483716373796671,
        0.8151628362620332
      ],
      [
        0.17687633624494703,
        0.8231236637550531
      ],
      [
        0.908810234945133,
        0.09118976505486709
      ],
      [
        0.08423431933486351,
        0.9157656806651365
      ],
      [
        0.26766037588604186,
        0.7323396241139581
      ],
      [
        0.025443563316154705,
        0.9745564366838454
      ],
      [
        0.17003039847950982,
        0.82996960152049
      ],
      [
        0.04909869270134342,
        0.9509013072986565
      ],
      [
        0.04464673483023972,
        0.95535326516976
      ],
      [
        0.17070397261753678,
        0.8292960273824633
      ],
      [
        0.1760541052044061,
        0.8239458947955938
      ],
      [
        0.053154256497423814,
        0.9468457435025763
      ],
      [
        0.11367207575497043,
        0.8863279242450297
      ],
      [
        0.5374253554620564,
        0.46257464453794356
      ],
      [
        0.07198291849804969,
        0.9280170815019504
      ],
      [
        0.814183060912997,
        0.18581693908700295
      ],
      [
        0.24243472287797466,
        0.7575652771220256
      ],
      [
        0.25311689767930495,
        0.7468831023206952
      ],
      [
        0.0268569461353311,
        0.9731430538646689
      ],
      [
        0.11833398809261116,
        0.881666011907389
      ],
      [
        0.13640140585490157,
        0.8635985941450985
      ],
      [
        0.07039141933033616,
        0.9296085806696639
      ],
      [
        0.9592127472532074,
        0.04078725274679267
      ],
      [
        0.1152401307151574,
        0.8847598692848428
      ],
      [
        0.31126138817112975,
        0.6887386118288701
      ],
      [
        0.08794757909222498,
        0.9120524209077749
      ],
      [
        0.09332261564956898,
        0.9066773843504311
      ],
      [
        0.47066291820757705,
        0.5293370817924228
      ],
      [
        0.01663096209196482,
        0.9833690379080353
      ],
      [
        0.9343019329688338,
        0.06569806703116648
      ],
      [
        0.17232861426837293,
        0.8276713857316271
      ],
      [
        0.862545996313952,
        0.13745400368604788
      ],
      [
        0.2034160269404405,
        0.7965839730595597
      ],
      [
        0.3997044353329083,
        0.6002955646670916
      ],
      [
        0.9163288659316737,
        0.08367113406832634
      ],
      [
        0.056005945604103505,
        0.9439940543958966
      ],
      [
        0.47884717212170713,
        0.5211528278782928
      ],
      [
        0.42334633296417207,
        0.576653667035828
      ],
      [
        0.8850818762120934,
        0.11491812378790649
      ],
      [
        0.3472782470845912,
        0.6527217529154088
      ],
      [
        0.951367165147754,
        0.048632834852246
      ],
      [
        0.05305565377249574,
        0.9469443462275043
      ],
      [
        0.13755046143120628,
        0.8624495385687938
      ],
      [
        0.8054182673279126,
        0.1945817326720875
      ],
      [
        0.591238226569439,
        0.4087617734305608
      ],
      [
        0.0779756096020619,
        0.922024390397938
      ],
      [
        0.2743865021266347,
        0.7256134978733653
      ],
      [
        0.7745097419593999,
        0.2254902580406
      ],
      [
        0.1731397466345228,
        0.8268602533654772
      ],
      [
        0.298621688505901,
        0.701378311494099
      ],
      [
        0.3492510018733781,
        0.650748998126622
      ],
      [
        0.06580237348531416,
        0.9341976265146857
      ],
      [
        0.33590663030170254,
        0.6640933696982972
      ],
      [
        0.08401283976458651,
        0.9159871602354137
      ],
      [
        0.5808549677783011,
        0.419145032221699
      ],
      [
        0.16685413378654726,
        0.8331458662134528
      ],
      [
        0.130833150189047,
        0.8691668498109533
      ],
      [
        0.049904351129689564,
        0.9500956488703106
      ],
      [
        0.1068128157046385,
        0.8931871842953614
      ],
      [
        0.21174842336872277,
        0.7882515766312773
      ],
      [
        0.4049694698401433,
        0.5950305301598565
      ],
      [
        0.4764738185790961,
        0.523526181420904
      ],
      [
        0.6815192411632847,
        0.31848075883671534
      ],
      [
        0.2793164928854236,
        0.7206835071145765
      ],
      [
        0.29065308139949864,
        0.7093469186005013
      ],
      [
        0.8442836577181136,
        0.15571634228188644
      ],
      [
        0.5703428382210503,
        0.4296571617789498
      ],
      [
        0.057983591806313385,
        0.9420164081936867
      ],
      [
        0.13932854356963256,
        0.8606714564303674
      ],
      [
        0.1034309238856401,
        0.89656907611436
      ],
      [
        0.12418916107463386,
        0.8758108389253659
      ],
      [
        0.5,
        0.5
      ],
      [
        0.022999404319624744,
        0.9770005956803752
      ],
      [
        0.1122423206716899,
        0.8877576793283101
      ],
      [
        0.09298763357360149,
        0.9070123664263987
      ],
      [
        0.0388558481914395,
        0.9611441518085604
      ],
      [
        0.07229878651529115,
        0.9277012134847089
      ],
      [
        0.20011640158374192,
        0.799883598416258
      ],
      [
        0.027708702508017966,
        0.9722912974919821
      ],
      [
        0.09629032315640991,
        0.9037096768435902
      ],
      [
        0.0910793924526848,
        0.908920607547315
      ],
      [
        0.05250492921072776,
        0.9474950707892723
      ],
      [
        0.33377842997951185,
        0.6662215700204882
      ],
      [
        0.04058307825356947,
        0.9594169217464306
      ],
      [
        0.064983257433174,
        0.935016742566826
      ],
      [
        0.19667467002281402,
        0.803325329977186
      ],
      [
        0.027595032752119362,
        0.9724049672478805
      ],
      [
        0.10329708379039518,
        0.896702916209605
      ],
      [
        0.4923243756551745,
        0.5076756243448256
      ],
      [
        0.8781380740565327,
        0.12186192594346731
      ],
      [
        0.47628260560003566,
        0.5237173943999645
      ],
      [
        0.019014131076305694,
        0.9809858689236941
      ],
      [
        0.17582549015730328,
        0.8241745098426967
      ],
      [
        0.774872120290145,
        0.22512787970985518
      ],
      [
        0.06172608012007872,
        0.9382739198799214
      ],
      [
        0.6957920219146696,
        0.3042079780853303
      ],
      [
        0.4529802056282543,
        0.5470197943717456
      ],
      [
        0.7438508728612678,
        0.2561491271387321
      ],
      [
        0.07392514586832959,
        0.9260748541316707
      ],
      [
        0.9380811692187301,
        0.06191883078126987
      ],
      [
        0.44535654023586035,
        0.5546434597641398
      ],
      [
        0.3983856200946328,
        0.601614379905367
      ],
      [
        0.7638799394193354,
        0.23612006058066487
      ],
      [
        0.766541171622901,
        0.23345882837709872
      ],
      [
        0.08060465708898577,
        0.9193953429110143
      ],
      [
        0.14072999708126666,
        0.8592700029187333
      ],
      [
        0.13438799119145628,
        0.8656120088085438
      ],
      [
        0.272647040540673,
        0.7273529594593269
      ],
      [
        0.10449089912828263,
        0.8955091008717175
      ],
      [
        0.05445923563559454,
        0.9455407643644053
      ],
      [
        0.4469176093496355,
        0.5530823906503646
      ],
      [
        0.7175367438280771,
        0.28246325617192297
      ],
      [
        0.08857777292507546,
        0.9114222270749244
      ],
      [
        0.03967908078164082,
        0.9603209192183594
      ],
      [
        0.028813509976847756,
        0.9711864900231522
      ],
      [
        0.40957615329798963,
        0.5904238467020103
      ],
      [
        0.24243472287797466,
        0.7575652771220256
      ],
      [
        0.8169155336178363,
        0.18308446638216386
      ],
      [
        0.5754697815406196,
        0.4245302184593805
      ],
      [
        0.06842318773550017,
        0.9315768122644998
      ],
      [
        0.0856834370525452,
        0.9143165629474549
      ],
      [
        0.6372701659364093,
        0.3627298340635908
      ],
      [
        0.2962117007846369,
        0.7037882992153632
      ],
      [
        0.5202758222836344,
        0.4797241777163656
      ],
      [
        0.34794307399240815,
        0.6520569260075918
      ],
      [
        0.06870347793513437,
        0.9312965220648656
      ],
      [
        0.24866656265910994,
        0.75133343734089
      ],
      [
        0.9581223776425919,
        0.041877622357408134
      ],
      [
        0.12555364425557375,
        0.8744463557444262
      ],
      [
        0.1664899077197691,
        0.8335100922802309
      ],
      [
        0.5414243724610335,
        0.45857562753896663
      ],
      [
        0.42767168817425477,
        0.5723283118257453
      ],
      [
        0.5703970550945735,
        0.42960294490542655
      ],
      [
        0.8269662167715116,
        0.17303378322848828
      ],
      [
        0.22459777483084656,
        0.7754022251691535
      ],
      [
        0.05352283319245038,
        0.9464771668075495
      ],
      [
        0.7769360546298761,
        0.22306394537012392
      ],
      [
        0.1343424635384994,
        0.8656575364615008
      ],
      [
        0.05549576150966613,
        0.944504238490334
      ],
      [
        0.100133901592405,
        0.899866098407595
      ],
      [
        0.5243637489300712,
        0.475636251069929
      ],
      [
        0.8033786058801349,
        0.19662139411986496
      ],
      [
        0.789750421716301,
        0.2102495782836989
      ],
      [
        0.3602638603733149,
        0.6397361396266851
      ],
      [
        0.41288938981506323,
        0.5871106101849367
      ],
      [
        0.6199470688294852,
        0.38005293117051464
      ],
      [
        0.9584048013472138,
        0.041595198652786186
      ],
      [
        0.05802403571239666,
        0.9419759642876033
      ],
      [
        0.21517158240904705,
        0.7848284175909529
      ],
      [
        0.22504206633315002,
        0.7749579336668503
      ],
      [
        0.5,
        0.5
      ],
      [
        0.18855141363975775,
        0.8114485863602423
      ],
      [
        0.3181265990744499,
        0.6818734009255499
      ],
      [
        0.8462157563536264,
        0.15378424364637377
      ],
      [
        0.12582553198717278,
        0.8741744680128273
      ],
      [
        0.6352289715891783,
        0.3647710284108217
      ],
      [
        0.060049715179460825,
        0.9399502848205393
      ],
      [
        0.764475051727759,
        0.23552494827224088
      ],
      [
        0.1060746026181802,
        0.8939253973818199
      ],
      [
        0.09294024118815838,
        0.9070597588118415
      ],
      [
        0.08309498447217731,
        0.9169050155278226
      ],
      [
        0.5077323352169146,
        0.4922676647830856
      ],
      [
        0.7320452334661699,
        0.2679547665338304
      ],
      [
        0.4061739326057004,
        0.5938260673942998
      ],
      [
        0.6781183619170198,
        0.32188163808298026
      ],
      [
        0.4583565431398785,
        0.5416434568601216
      ],
      [
        0.7363901517618313,
        0.26360984823816874
      ],
      [
        0.027669162624578063,
        0.972330837375422
      ],
      [
        0.17701289344124835,
        0.822987106558752
      ],
      [
        0.07394186295688036,
        0.9260581370431197
      ],
      [
        0.8546675524058279,
        0.14533244759417202
      ],
      [
        0.7014802475361019,
        0.2985197524638979
      ],
      [
        0.7827565991925708,
        0.21724340080742913
      ],
      [
        0.11387780064542727,
        0.8861221993545727
      ],
      [
        0.31086955674600053,
        0.6891304432539995
      ],
      [
        0.042110759037537304,
        0.9578892409624626
      ],
      [
        0.15553184349982993,
        0.8444681565001702
      ],
      [
        0.15745611863858355,
        0.8425438813614164
      ],
      [
        0.029195481700786542,
        0.9708045182992132
      ]
    ]
  },
  "train_accuracy": 0.9970699037254082,
  "num_features": 4715,
  "label_mapping": {
    "clickbait": 0,
    "non-clickbait": 1
  }
}